{
  "meta": {
    "titleTemplate": "%s",
    "siteUrl": "https://foundation.stackrole.com",
    "image": "/assets/stackrole.png",
    "iconimage": "/assets/stackrole.png",
    "social": {
      "github": {
        "title": "github",
        "username": "",
        "url": "https://github.com/"
      },
      "twitter": {
        "title": "twitter",
        "username": "",
        "url": "https://twitter.com/"
      },
      "instagram": {
        "title": "instagram",
        "username": "",
        "url": "https://www.instagram.com/"
      },
      "email": {
        "title": "email",
        "username": "",
        "url": "mailto:` }"
      }
    },
    "author": {
      "summary": "",
      "profile": "../assets/profile-pic.png",
      "name": ""
    },
    "description": "",
    "title": ""
  },
  "ga": "UA-XXXXXXXXX-X"
}